wofry/__init__.py
wofry/version.py
wofry/beamline/__init__.py
wofry/beamline/decorators.py
wofry/propagator/__init__.py
wofry/propagator/decorators.py
wofry/propagator/polarization.py
wofry/propagator/propagator.py
wofry/propagator/wavefront.py
wofry/propagator/util/__init__.py
wofry/propagator/util/gaussian_schell_model.py
wofry/propagator/wavefront1D/__init__.py
wofry/propagator/wavefront1D/generic_wavefront.py
wofry/propagator/wavefront2D/__init__.py
wofry/propagator/wavefront2D/generic_wavefront.py
wofry-1.0.34.dist-info/licenses/LICENSE
wofry-1.0.34.dist-info/METADATA
wofry-1.0.34.dist-info/WHEEL
wofry-1.0.34.dist-info/top_level.txt
wofry-1.0.34.dist-info/RECORD
