Metadata-Version: 2.4
Name: wofry
Version: 1.0.34
Summary: WOFRY (Wave Optics FRamework in pYthon) kernel library
Home-page: https://github.com/oasys-kit/wofry
Download-URL: https://github.com/oasys-kit/wofry
Author: Manuel Sanchez del Rio, Luca Rebuffi
Author-email: lrebuffi@anl.gov
Maintainer: Luca Rebuffi
Maintainer-email: lrebuffi@anl.gov
License: GPLv3
Keywords: dictionary,glossary,synchrotronsimulation
Classifier: Development Status :: 5 - Production/Stable
Classifier: Environment :: Console
Classifier: Environment :: Plugins
Classifier: Programming Language :: Python :: 3
Classifier: Operating System :: POSIX
Classifier: Operating System :: Microsoft :: Windows
Classifier: Topic :: Scientific/Engineering :: Visualization
Classifier: Topic :: Software Development :: Libraries :: Python Modules
Classifier: Intended Audience :: Education
Classifier: Intended Audience :: Science/Research
Classifier: Intended Audience :: Developers
License-File: LICENSE
Requires-Dist: syned>=1.0.26
Requires-Dist: h5py
Requires-Dist: srxraylib>=1.0.46
Dynamic: author
Dynamic: author-email
Dynamic: classifier
Dynamic: description
Dynamic: download-url
Dynamic: home-page
Dynamic: keywords
Dynamic: license
Dynamic: license-file
Dynamic: maintainer
Dynamic: maintainer-email
Dynamic: requires-dist
Dynamic: summary
